transformative_harmonization/__init__.py
transformative_harmonization/core.py
transformative_harmonization/custom.py
transformative_harmonization/matrix.py
transformative_harmonization/vector.py
transformative_harmonization-0.2.2.dist-info/licenses/LICENSE.txt
transformative_harmonization-0.2.2.dist-info/METADATA
transformative_harmonization-0.2.2.dist-info/WHEEL
transformative_harmonization-0.2.2.dist-info/top_level.txt
transformative_harmonization-0.2.2.dist-info/RECORD
