Metadata-Version: 2.4
Name: transformative_harmonization
Version: 0.2.2
Summary: A Python library for Transformative Harmonization, a novel similarity metric
Home-page: https://github.com/Zayn/transformative_harmonization
Author: Zayn
Classifier: Programming Language :: Python :: 3
Classifier: License :: OSI Approved :: MIT License
Classifier: Operating System :: OS Independent
Classifier: Topic :: Scientific/Engineering :: Artificial Intelligence
Requires-Python: >=3.7
License-File: LICENSE.txt
Requires-Dist: numpy>=1.21.0
Requires-Dist: scikit-learn>=1.0.0
Dynamic: author
Dynamic: classifier
Dynamic: description
Dynamic: description-content-type
Dynamic: home-page
Dynamic: license-file
Dynamic: requires-dist
Dynamic: requires-python
Dynamic: summary
